robotframework_tidy-4.18.0.dist-info/licenses/LICENSE
robotidy/__init__.py
robotidy/__main__.py
robotidy/api.py
robotidy/app.py
robotidy/cli.py
robotidy/config.py
robotidy/decorators.py
robotidy/disablers.py
robotidy/exceptions.py
robotidy/files.py
robotidy/rich_console.py
robotidy/skip.py
robotidy/version.py
robotidy/__pycache__/__init__.cpython-313.pyc
robotidy/__pycache__/version.cpython-313.pyc
robotidy/transformers/AddMissingEnd.py
robotidy/transformers/AlignKeywordsSection.py
robotidy/transformers/AlignSettingsSection.py
robotidy/transformers/AlignTemplatedTestCases.py
robotidy/transformers/AlignTestCasesSection.py
robotidy/transformers/AlignVariablesSection.py
robotidy/transformers/DiscardEmptySections.py
robotidy/transformers/GenerateDocumentation.py
robotidy/transformers/IndentNestedKeywords.py
robotidy/transformers/InlineIf.py
robotidy/transformers/MergeAndOrderSections.py
robotidy/transformers/NormalizeAssignments.py
robotidy/transformers/NormalizeComments.py
robotidy/transformers/NormalizeNewLines.py
robotidy/transformers/NormalizeSectionHeaderName.py
robotidy/transformers/NormalizeSeparators.py
robotidy/transformers/NormalizeSettingName.py
robotidy/transformers/NormalizeTags.py
robotidy/transformers/OrderSettings.py
robotidy/transformers/OrderSettingsSection.py
robotidy/transformers/OrderTags.py
robotidy/transformers/RemoveEmptySettings.py
robotidy/transformers/RenameKeywords.py
robotidy/transformers/RenameTestCases.py
robotidy/transformers/RenameVariables.py
robotidy/transformers/ReplaceBreakContinue.py
robotidy/transformers/ReplaceEmptyValues.py
robotidy/transformers/ReplaceReturns.py
robotidy/transformers/ReplaceRunKeywordIf.py
robotidy/transformers/ReplaceWithVAR.py
robotidy/transformers/SmartSortKeywords.py
robotidy/transformers/SplitTooLongLine.py
robotidy/transformers/Translate.py
robotidy/transformers/__init__.py
robotidy/transformers/aligners_core.py
robotidy/transformers/run_keywords.py
robotidy/utils/misc.py
robotidy/utils/variable_matcher.py
robotframework_tidy-4.18.0.dist-info/METADATA
robotframework_tidy-4.18.0.dist-info/WHEEL
robotframework_tidy-4.18.0.dist-info/entry_points.txt
robotframework_tidy-4.18.0.dist-info/top_level.txt
robotframework_tidy-4.18.0.dist-info/RECORD
