Metadata-Version: 2.4
Name: robotframework-tidy
Version: 4.18.0
Summary: Code autoformatter for Robot Framework
Home-page: https://github.com/MarketSquare/robotframework-tidy
Author: MarketSquare - Robot Framework community
Author-email: bartek.hirsz@gmail.com
License: Apache License 2.0
Keywords: robotframework
Platform: any
Classifier: Development Status :: 5 - Production/Stable
Classifier: License :: OSI Approved :: Apache Software License
Classifier: Operating System :: OS Independent
Classifier: Programming Language :: Python
Classifier: Programming Language :: Python :: 3.8
Classifier: Programming Language :: Python :: 3.9
Classifier: Programming Language :: Python :: 3.10
Classifier: Programming Language :: Python :: 3.11
Classifier: Programming Language :: Python :: 3.12
Classifier: Framework :: Robot Framework
Classifier: Framework :: Robot Framework :: Tool
Classifier: Topic :: Software Development :: Testing
Classifier: Topic :: Software Development :: Quality Assurance
Classifier: Topic :: Utilities
Classifier: Intended Audience :: Developers
Requires-Python: >=3.8
License-File: LICENSE
Requires-Dist: robotframework>=4.0
Requires-Dist: click>=8.1
Requires-Dist: colorama>=0.4.3
Requires-Dist: pathspec>=0.9.0
Requires-Dist: tomli>=2.0
Requires-Dist: rich_click>=1.4
Requires-Dist: jinja2>=3.1.3
Provides-Extra: dev
Requires-Dist: coverage; extra == "dev"
Requires-Dist: invoke; extra == "dev"
Requires-Dist: jinja2; extra == "dev"
Requires-Dist: packaging>=21.0; extra == "dev"
Requires-Dist: pyflakes<3.3,>=2.4; extra == "dev"
Requires-Dist: pylama; extra == "dev"
Requires-Dist: pytest; extra == "dev"
Requires-Dist: pre-commit; extra == "dev"
Requires-Dist: tomli_w<1.2,>=1.0; extra == "dev"
Provides-Extra: doc
Requires-Dist: sphinx; extra == "doc"
Requires-Dist: furo; extra == "doc"
Requires-Dist: sphinx-design; extra == "doc"
Requires-Dist: sphinx-copybutton==0.5.2; extra == "doc"
Provides-Extra: generate-config
Requires-Dist: tomli_w<1.2,>=1.0; extra == "generate-config"
Dynamic: author
Dynamic: author-email
Dynamic: classifier
Dynamic: description
Dynamic: description-content-type
Dynamic: home-page
Dynamic: keywords
Dynamic: license
Dynamic: license-file
Dynamic: platform
Dynamic: provides-extra
Dynamic: requires-dist
Dynamic: requires-python
Dynamic: summary
